{"uuids": {"phone_id": "6adb4017-6f48-4bdf-bb5d-26b2937d6525", "uuid": "e75c87e0-90a7-48ed-9e99-2229260eefc7", "client_session_id": "188a9dc2-4946-497b-b020-c78671871abf", "advertising_id": "2b2d16ea-dda5-4a44-b439-cfdbfae1135f", "device_id": "android-65bce64ad98bdd9e"}, "cookie": {"csrftoken": "khrDtKW9EseJNOD3dc1lBasD0bStsAWr", "ds_user": "a_the_rva", "ds_user_id": "8420974379", "ig_direct_region_hint": "LLA", "mid": "X91OKgABAAHk9-N5GuM_mhI7pwOa", "rur": "VLL", "sessionid": "8420974379%3Aat6ZIt6dnw4Uzw%3A12", "shbid": "3824", "shbts": "1608338990.9125295", "urlgen": "\"{117.196.99.101: 9829}:1kqRdI:DPNOLhrWd6od-b0_J3wsdMZ1mJo\""}, "timing_value": {"last_login": 1608343534.4938576, "last_experiments": 1608343566.4152627}, "device_settings": {"app_version": "117.0.0.28.123", "android_version": "28", "android_release": "9.0", "dpi": "420dpi", "resolution": "1080x1920", "manufacturer": "OnePlus", "device": "ONEPLUS A3003", "model": "OnePlus3", "cpu": "qcom", "version_code": "180322800"}, "user_agent": "Instagram 117.0.0.28.123 Android (28/9.0; 420dpi; 1080x1920; OnePlus; ONEPLUS A3003; OnePlus3; qcom; en_US; 180322800)"}